{
  "type": "FeatureCollection",
  "features": [
    {
      "type": "Feature",
      "geometry": {
        "type": "Point",
        "coordinates": [
          44.49666667,
          40.11416667
        ]
      },
      "properties": {
        "label": "Yerevan Thermal Power Plant",
        "type": "Gas-fired power station",
        "entity": "http://www.wikidata.org/entity/Q21777838",
        "country_qid": "Q399"
      }
    }
  ]
}