{
  "type": "FeatureCollection",
  "features": [
    {
      "type": "Feature",
      "geometry": {
        "type": "Point",
        "coordinates": [
          17.68972222,
          48.45833333
        ]
      },
      "properties": {
        "label": "Malženice power plant",
        "type": "Gas-fired power station",
        "entity": "http://www.wikidata.org/entity/Q173970",
        "country_qid": "Q214"
      }
    },
    {
      "type": "Feature",
      "geometry": {
        "type": "Point",
        "coordinates": [
          17.1543145,
          48.1770363
        ]
      },
      "properties": {
        "label": "PPC Bratislava power plant",
        "type": "Gas-fired power station",
        "entity": "http://www.wikidata.org/entity/Q11962117",
        "country_qid": "Q214"
      }
    }
  ]
}