{
  "type": "FeatureCollection",
  "features": [
    {
      "type": "Feature",
      "geometry": {
        "type": "Point",
        "coordinates": [
          -56.236635,
          -34.826503
        ]
      },
      "properties": {
        "label": "La Tablada Power Plant",
        "type": "Gas-fired power station",
        "entity": "http://www.wikidata.org/entity/Q11982886",
        "country_qid": "Q77"
      }
    },
    {
      "type": "Feature",
      "geometry": {
        "type": "Point",
        "coordinates": [
          -56.541722,
          -34.751167
        ]
      },
      "properties": {
        "label": "Punta del Tigre Power Plant",
        "type": "Gas-fired power station",
        "entity": "http://www.wikidata.org/entity/Q30973056",
        "country_qid": "Q77"
      }
    }
  ]
}