{
  "type": "FeatureCollection",
  "features": [
    {
      "type": "Feature",
      "geometry": {
        "type": "Point",
        "coordinates": [
          139.66,
          35.29
        ]
      },
      "properties": {
        "label": "Yokosuka Naval Arsenal",
        "type": "Hydraulic structure",
        "entity": "http://www.wikidata.org/entity/Q2790777",
        "country_qid": "Q188712"
      }
    },
    {
      "type": "Feature",
      "geometry": {
        "type": "Point",
        "coordinates": [
          137.373,
          34.834
        ]
      },
      "properties": {
        "label": "Toyokawa Naval Arsenal",
        "type": "Hydraulic structure",
        "entity": "http://www.wikidata.org/entity/Q2753675",
        "country_qid": "Q188712"
      }
    }
  ]
}