{
  "type": "FeatureCollection",
  "features": [
    {
      "type": "Feature",
      "geometry": {
        "type": "Point",
        "coordinates": [
          -79.2808,
          25.7471
        ]
      },
      "properties": {
        "label": "Fisherman's Village Marina",
        "type": "Hydraulic structure",
        "entity": "http://www.wikidata.org/entity/Q113257203",
        "country_qid": "Q778"
      }
    },
    {
      "type": "Feature",
      "geometry": {
        "type": "Point",
        "coordinates": [
          -78.216666666,
          26.616666666
        ]
      },
      "properties": {
        "label": "South Riding Point",
        "type": "Hydraulic structure",
        "entity": "http://www.wikidata.org/entity/Q111386626",
        "country_qid": "Q778"
      }
    },
    {
      "type": "Feature",
      "geometry": {
        "type": "Point",
        "coordinates": [
          -78.55,
          26.55
        ]
      },
      "properties": {
        "label": "Grand Lucayan Waterway",
        "type": "Hydraulic structure",
        "entity": "http://www.wikidata.org/entity/Q21714020",
        "country_qid": "Q778"
      }
    },
    {
      "type": "Feature",
      "geometry": {
        "type": "Point",
        "coordinates": [
          -76.999825,
          26.327652777
        ]
      },
      "properties": {
        "label": "Little Harbour",
        "type": "Hydraulic structure",
        "entity": "http://www.wikidata.org/entity/Q14214303",
        "country_qid": "Q778"
      }
    },
    {
      "type": "Feature",
      "geometry": {
        "type": "Point",
        "coordinates": [
          -78.76667,
          26.5
        ]
      },
      "properties": {
        "label": "Freeport Harbour",
        "type": "Hydraulic structure",
        "entity": "http://www.wikidata.org/entity/Q21713982",
        "country_qid": "Q778"
      }
    }
  ]
}