{
  "type": "FeatureCollection",
  "features": [
    {
      "type": "Feature",
      "geometry": {
        "type": "Point",
        "coordinates": [
          106.7576051,
          20.9421021
        ]
      },
      "properties": {
        "label": "Hai Phong Thermal Power Station",
        "type": "Coal-fired power station",
        "entity": "http://www.wikidata.org/entity/Q17779747",
        "country_qid": "Q881"
      }
    },
    {
      "type": "Feature",
      "geometry": {
        "type": "Point",
        "coordinates": [
          106.309,
          21.1155
        ]
      },
      "properties": {
        "label": "Pha Lai Power Station",
        "type": "Coal-fired power station",
        "entity": "http://www.wikidata.org/entity/Q7179855",
        "country_qid": "Q881"
      }
    },
    {
      "type": "Feature",
      "geometry": {
        "type": "Point",
        "coordinates": [
          106.7858934,
          21.0400352
        ]
      },
      "properties": {
        "label": "Uông Bí Power Station",
        "type": "Coal-fired power station",
        "entity": "http://www.wikidata.org/entity/Q12008544",
        "country_qid": "Q881"
      }
    },
    {
      "type": "Feature",
      "geometry": {
        "type": "Point",
        "coordinates": [
          106.5775001,
          21.0899157
        ]
      },
      "properties": {
        "label": "Q10800795",
        "type": "Coal-fired power station",
        "entity": "http://www.wikidata.org/entity/Q10800795",
        "country_qid": "Q881"
      }
    },
    {
      "type": "Feature",
      "geometry": {
        "type": "Point",
        "coordinates": [
          108.7983799,
          11.3168815
        ]
      },
      "properties": {
        "label": "Vinh Tan 3 Power Plant",
        "type": "Coal-fired power station",
        "entity": "http://www.wikidata.org/entity/Q130358624",
        "country_qid": "Q881"
      }
    },
    {
      "type": "Feature",
      "geometry": {
        "type": "Point",
        "coordinates": [
          108.8071239,
          11.3184595
        ]
      },
      "properties": {
        "label": "Vinh Tan 1 Power Plant",
        "type": "Coal-fired power station",
        "entity": "http://www.wikidata.org/entity/Q130358584",
        "country_qid": "Q881"
      }
    },
    {
      "type": "Feature",
      "geometry": {
        "type": "Point",
        "coordinates": [
          108.7943244,
          11.3163713
        ]
      },
      "properties": {
        "label": "Vinh Tan 4 Power Plant",
        "type": "Coal-fired power station",
        "entity": "http://www.wikidata.org/entity/Q130358623",
        "country_qid": "Q881"
      }
    },
    {
      "type": "Feature",
      "geometry": {
        "type": "Point",
        "coordinates": [
          106.7796528,
          21.1794598
        ]
      },
      "properties": {
        "label": "Q10800847",
        "type": "Coal-fired power station",
        "entity": "http://www.wikidata.org/entity/Q10800847",
        "country_qid": "Q881"
      }
    },
    {
      "type": "Feature",
      "geometry": {
        "type": "Point",
        "coordinates": [
          106.3811195,
          18.0980448
        ]
      },
      "properties": {
        "label": "Q10800851",
        "type": "Coal-fired power station",
        "entity": "http://www.wikidata.org/entity/Q10800851",
        "country_qid": "Q881"
      }
    },
    {
      "type": "Feature",
      "geometry": {
        "type": "Point",
        "coordinates": [
          108.8026178,
          11.3176495
        ]
      },
      "properties": {
        "label": "Vinh Tan 2 Power Plant",
        "type": "Coal-fired power station",
        "entity": "http://www.wikidata.org/entity/Q130358625",
        "country_qid": "Q881"
      }
    },
    {
      "type": "Feature",
      "geometry": {
        "type": "Point",
        "coordinates": [
          106.527222,
          9.583333
        ]
      },
      "properties": {
        "label": "Duyen Hai Power Station",
        "type": "Coal-fired power station",
        "entity": "http://www.wikidata.org/entity/Q5317674",
        "country_qid": "Q881"
      }
    },
    {
      "type": "Feature",
      "geometry": {
        "type": "Point",
        "coordinates": [
          107.3574328,
          21.006818
        ]
      },
      "properties": {
        "label": "Q10800845",
        "type": "Coal-fired power station",
        "entity": "http://www.wikidata.org/entity/Q10800845",
        "country_qid": "Q881"
      }
    }
  ]
}