{
  "type": "FeatureCollection",
  "features": [
    {
      "type": "Feature",
      "geometry": {
        "type": "Point",
        "coordinates": [
          -5.86171667,
          41.47927778
        ]
      },
      "properties": {
        "label": "San Román Dam",
        "type": "Hydroelectric dam",
        "entity": "http://www.wikidata.org/entity/Q6085406",
        "country_qid": "Q29"
      }
    }
  ]
}