{
  "type": "FeatureCollection",
  "features": [
    {
      "type": "Feature",
      "geometry": {
        "type": "Point",
        "coordinates": [
          -15.518055555,
          13.436944444
        ]
      },
      "properties": {
        "label": "Soma Solar Power Station",
        "type": "Solar power station",
        "entity": "http://www.wikidata.org/entity/Q111947629",
        "country_qid": "Q1005"
      }
    },
    {
      "type": "Feature",
      "geometry": {
        "type": "Point",
        "coordinates": [
          -16.690555555,
          13.306388888
        ]
      },
      "properties": {
        "label": "Jambur Solar Power Station",
        "type": "Solar power station",
        "entity": "http://www.wikidata.org/entity/Q125635132",
        "country_qid": "Q1005"
      }
    }
  ]
}