{
  "type": "FeatureCollection",
  "features": [
    {
      "type": "Feature",
      "geometry": {
        "type": "Point",
        "coordinates": [
          0.17444444,
          10.84166667
        ]
      },
      "properties": {
        "label": "Dapaong Solar Power Station",
        "type": "Solar power station",
        "entity": "http://www.wikidata.org/entity/Q125867233",
        "country_qid": "Q945"
      }
    },
    {
      "type": "Feature",
      "geometry": {
        "type": "Point",
        "coordinates": [
          1.225833333,
          9.413888888
        ]
      },
      "properties": {
        "label": "Kpalassi Solar Power Station",
        "type": "Solar power station",
        "entity": "http://www.wikidata.org/entity/Q112892598",
        "country_qid": "Q945"
      }
    },
    {
      "type": "Feature",
      "geometry": {
        "type": "Point",
        "coordinates": [
          1.010277777,
          8.307777777
        ]
      },
      "properties": {
        "label": "Blitta Solar Power Station",
        "type": "Solar power station",
        "entity": "http://www.wikidata.org/entity/Q107481956",
        "country_qid": "Q945"
      }
    },
    {
      "type": "Feature",
      "geometry": {
        "type": "Point",
        "coordinates": [
          1.195277777,
          6.323055555
        ]
      },
      "properties": {
        "label": "Adétikopé Solar Power Station",
        "type": "Solar power station",
        "entity": "http://www.wikidata.org/entity/Q108730487",
        "country_qid": "Q945"
      }
    }
  ]
}