{
  "type": "FeatureCollection",
  "features": [
    {
      "type": "Feature",
      "geometry": {
        "type": "Point",
        "coordinates": [
          -3.269166666,
          5.439444444
        ]
      },
      "properties": {
        "label": "Ayebo Biomass Power Station",
        "type": "Thermal power station",
        "entity": "http://www.wikidata.org/entity/Q107292934",
        "country_qid": "Q1008"
      }
    },
    {
      "type": "Feature",
      "geometry": {
        "type": "Point",
        "coordinates": [
          -6.503333333,
          9.491944444
        ]
      },
      "properties": {
        "label": "Boundiali Biomass Power Station",
        "type": "Thermal power station",
        "entity": "http://www.wikidata.org/entity/Q123515704",
        "country_qid": "Q1008"
      }
    },
    {
      "type": "Feature",
      "geometry": {
        "type": "Point",
        "coordinates": [
          -4.009555555,
          5.261444444
        ]
      },
      "properties": {
        "label": "Q56373411",
        "type": "Thermal power station",
        "entity": "http://www.wikidata.org/entity/Q56373411",
        "country_qid": "Q1008"
      }
    },
    {
      "type": "Feature",
      "geometry": {
        "type": "Point",
        "coordinates": [
          -4.076111111,
          5.301111111
        ]
      },
      "properties": {
        "label": "Q18642451",
        "type": "Thermal power station",
        "entity": "http://www.wikidata.org/entity/Q18642451",
        "country_qid": "Q1008"
      }
    },
    {
      "type": "Feature",
      "geometry": {
        "type": "Point",
        "coordinates": [
          -4.007972222,
          5.257972222
        ]
      },
      "properties": {
        "label": "Q19406854",
        "type": "Thermal power station",
        "entity": "http://www.wikidata.org/entity/Q19406854",
        "country_qid": "Q1008"
      }
    },
    {
      "type": "Feature",
      "geometry": {
        "type": "Point",
        "coordinates": [
          -4.328888888,
          5.255833333
        ]
      },
      "properties": {
        "label": "Atinkou Thermal Power Station",
        "type": "Thermal power station",
        "entity": "http://www.wikidata.org/entity/Q106936014",
        "country_qid": "Q1008"
      }
    }
  ]
}