{
  "type": "FeatureCollection",
  "features": [
    {
      "type": "Feature",
      "geometry": {
        "type": "Point",
        "coordinates": [
          5.51111111,
          59.27555556
        ]
      },
      "properties": {
        "label": "Kårstø Power Station",
        "type": "Thermal power station",
        "entity": "http://www.wikidata.org/entity/Q6453647",
        "country_qid": "Q20"
      }
    },
    {
      "type": "Feature",
      "geometry": {
        "type": "Point",
        "coordinates": [
          5.03694444,
          60.80888889
        ]
      },
      "properties": {
        "label": "Mongstad Power Station",
        "type": "Thermal power station",
        "entity": "http://www.wikidata.org/entity/Q6899813",
        "country_qid": "Q20"
      }
    },
    {
      "type": "Feature",
      "geometry": {
        "type": "Point",
        "coordinates": [
          15.6186,
          78.2253
        ]
      },
      "properties": {
        "label": "Longyear Energiverk",
        "type": "Thermal power station",
        "entity": "http://www.wikidata.org/entity/Q11986759",
        "country_qid": "Q20"
      }
    },
    {
      "type": "Feature",
      "geometry": {
        "type": "Point",
        "coordinates": [
          5.69666667,
          58.88333333
        ]
      },
      "properties": {
        "label": "Q17761233",
        "type": "Thermal power station",
        "entity": "http://www.wikidata.org/entity/Q17761233",
        "country_qid": "Q20"
      }
    },
    {
      "type": "Feature",
      "geometry": {
        "type": "Point",
        "coordinates": [
          8.6578,
          63.4097
        ]
      },
      "properties": {
        "label": "Tjeldbergodden Reserve Power Station",
        "type": "Thermal power station",
        "entity": "http://www.wikidata.org/entity/Q7810606",
        "country_qid": "Q20"
      }
    },
    {
      "type": "Feature",
      "geometry": {
        "type": "Point",
        "coordinates": [
          16.39,
          78.657
        ]
      },
      "properties": {
        "label": "Q19385861",
        "type": "Thermal power station",
        "entity": "http://www.wikidata.org/entity/Q19385861",
        "country_qid": "Q20"
      }
    },
    {
      "type": "Feature",
      "geometry": {
        "type": "Point",
        "coordinates": [
          14.212,
          78.055
        ]
      },
      "properties": {
        "label": "Q11960204",
        "type": "Thermal power station",
        "entity": "http://www.wikidata.org/entity/Q11960204",
        "country_qid": "Q20"
      }
    },
    {
      "type": "Feature",
      "geometry": {
        "type": "Point",
        "coordinates": [
          10.836389,
          59.840833
        ]
      },
      "properties": {
        "label": "Q19377435",
        "type": "Thermal power station",
        "entity": "http://www.wikidata.org/entity/Q19377435",
        "country_qid": "Q20"
      }
    }
  ]
}