{
  "type": "FeatureCollection",
  "features": [
    {
      "type": "Feature",
      "geometry": {
        "type": "Point",
        "coordinates": [
          -115.009444444,
          35.801111111
        ]
      },
      "properties": {
        "label": "Path 62",
        "type": "Underground power cable",
        "entity": "http://www.wikidata.org/entity/Q7144630",
        "country_qid": "Q30"
      }
    },
    {
      "type": "Feature",
      "geometry": {
        "type": "Point",
        "coordinates": [
          -121.114166666,
          45.594166666
        ]
      },
      "properties": {
        "label": "Pacific DC Intertie",
        "type": "Underground power cable",
        "entity": "http://www.wikidata.org/entity/Q2045524",
        "country_qid": "Q30"
      }
    },
    {
      "type": "Feature",
      "geometry": {
        "type": "Point",
        "coordinates": [
          -73.6797,
          42.8781
        ]
      },
      "properties": {
        "label": "HVDC Mechanicville–Schenectady",
        "type": "Underground power cable",
        "entity": "http://www.wikidata.org/entity/Q5636205",
        "country_qid": "Q30"
      }
    }
  ]
}