{
  "type": "FeatureCollection",
  "features": [
    {
      "type": "Feature",
      "geometry": {
        "type": "Point",
        "coordinates": [
          -175.118916666,
          -21.265666666
        ]
      },
      "properties": {
        "label": "Nakolo Wind Turbine",
        "type": "power plant",
        "entity": "http://www.wikidata.org/entity/Q123357869",
        "country_qid": "Q678"
      }
    },
    {
      "type": "Feature",
      "geometry": {
        "type": "Point",
        "coordinates": [
          -175.190166666,
          -21.189972222
        ]
      },
      "properties": {
        "label": "Mata ʻo e Laʻa Solar Facility",
        "type": "power plant",
        "entity": "http://www.wikidata.org/entity/Q124338526",
        "country_qid": "Q678"
      }
    },
    {
      "type": "Feature",
      "geometry": {
        "type": "Point",
        "coordinates": [
          -175.348222222,
          -21.1005
        ]
      },
      "properties": {
        "label": "Sunergise 6 MW IPP Solar Generation Systems",
        "type": "power plant",
        "entity": "http://www.wikidata.org/entity/Q124338542",
        "country_qid": "Q678"
      }
    },
    {
      "type": "Feature",
      "geometry": {
        "type": "Point",
        "coordinates": [
          -175.180444444,
          -21.157833333
        ]
      },
      "properties": {
        "label": "Maama Mai Solar Farm",
        "type": "power plant",
        "entity": "http://www.wikidata.org/entity/Q124338546",
        "country_qid": "Q678"
      }
    }
  ]
}