{
  "type": "FeatureCollection",
  "features": [
    {
      "type": "Feature",
      "geometry": {
        "type": "Point",
        "coordinates": [
          -74.07361111,
          4.59666667
        ]
      },
      "properties": {
        "label": "Casa de Moneda de Colombia",
        "type": "Industrial building",
        "entity": "http://www.wikidata.org/entity/Q3279784",
        "country_qid": "Q739"
      }
    },
    {
      "type": "Feature",
      "geometry": {
        "type": "Point",
        "coordinates": [
          -75.14651,
          4.40076
        ]
      },
      "properties": {
        "label": "Fábrica de Moneda",
        "type": "Industrial building",
        "entity": "http://www.wikidata.org/entity/Q124980863",
        "country_qid": "Q739"
      }
    },
    {
      "type": "Feature",
      "geometry": {
        "type": "Point",
        "coordinates": [
          -76.539344444,
          3.447791666
        ]
      },
      "properties": {
        "label": "La Linterna Cali",
        "type": "Industrial building",
        "entity": "http://www.wikidata.org/entity/Q134800300",
        "country_qid": "Q739"
      }
    },
    {
      "type": "Feature",
      "geometry": {
        "type": "Point",
        "coordinates": [
          -75.49722222,
          10.315
        ]
      },
      "properties": {
        "label": "Cartagena Refinery",
        "type": "Industrial building",
        "entity": "http://www.wikidata.org/entity/Q3417387",
        "country_qid": "Q739"
      }
    }
  ]
}