{
  "type": "FeatureCollection",
  "features": [
    {
      "type": "Feature",
      "geometry": {
        "type": "Point",
        "coordinates": [
          -13.501718,
          9.722947
        ]
      },
      "properties": {
        "label": "Q108421709",
        "type": "Industrial building",
        "entity": "http://www.wikidata.org/entity/Q108421709",
        "country_qid": "Q1006"
      }
    },
    {
      "type": "Feature",
      "geometry": {
        "type": "Point",
        "coordinates": [
          -13.57824,
          10.38698
        ]
      },
      "properties": {
        "label": "Fria aluminum factory",
        "type": "Industrial building",
        "entity": "http://www.wikidata.org/entity/Q117409275",
        "country_qid": "Q1006"
      }
    }
  ]
}