{
  "type": "FeatureCollection",
  "features": [
    {
      "type": "Feature",
      "geometry": {
        "type": "Point",
        "coordinates": [
          -76.277732849,
          -10.672732919
        ]
      },
      "properties": {
        "label": "Pasco electrical substation",
        "type": "Electrical substation",
        "entity": "http://www.wikidata.org/entity/Q113324390",
        "country_qid": "Q419"
      }
    }
  ]
}