{
  "type": "FeatureCollection",
  "features": [
    {
      "type": "Feature",
      "geometry": {
        "type": "Point",
        "coordinates": [
          2.6769,
          57.5672
        ]
      },
      "properties": {
        "label": "North Sea Link",
        "type": "Overhead power line",
        "entity": "http://www.wikidata.org/entity/Q5636209",
        "country_qid": "Q145"
      }
    }
  ]
}