{
  "type": "FeatureCollection",
  "features": [
    {
      "type": "Feature",
      "geometry": {
        "type": "Point",
        "coordinates": [
          25.0,
          20.0
        ]
      },
      "properties": {
        "label": "Nubian Sandstone Aquifer System",
        "type": "Reservoir",
        "entity": "http://www.wikidata.org/entity/Q1530545",
        "country_qid": "Q657"
      }
    },
    {
      "type": "Feature",
      "geometry": {
        "type": "Point",
        "coordinates": [
          15.1037,
          12.1017
        ]
      },
      "properties": {
        "label": "Q134429865",
        "type": "Reservoir",
        "entity": "http://www.wikidata.org/entity/Q134429865",
        "country_qid": "Q657"
      }
    }
  ]
}