{
  "type": "FeatureCollection",
  "features": [
    {
      "type": "Feature",
      "geometry": {
        "type": "Point",
        "coordinates": [
          -60.666666666,
          11.227777777
        ]
      },
      "properties": {
        "label": "Hillsborough Reservoir",
        "type": "Reservoir",
        "entity": "http://www.wikidata.org/entity/Q5763721",
        "country_qid": "Q754"
      }
    },
    {
      "type": "Feature",
      "geometry": {
        "type": "Point",
        "coordinates": [
          -61.183333333,
          10.7
        ]
      },
      "properties": {
        "label": "Hollis Reservoir",
        "type": "Reservoir",
        "entity": "http://www.wikidata.org/entity/Q7346437",
        "country_qid": "Q754"
      }
    }
  ]
}