{
  "type": "FeatureCollection",
  "features": [
    {
      "type": "Feature",
      "geometry": {
        "type": "Point",
        "coordinates": [
          35.0255,
          -15.792416666
        ]
      },
      "properties": {
        "label": "Q56373991",
        "type": "Thermal power station",
        "entity": "http://www.wikidata.org/entity/Q56373991",
        "country_qid": "Q1020"
      }
    },
    {
      "type": "Feature",
      "geometry": {
        "type": "Point",
        "coordinates": [
          34.84361111,
          -15.46
        ]
      },
      "properties": {
        "label": "Kammwamba Thermal Power Station",
        "type": "Thermal power station",
        "entity": "http://www.wikidata.org/entity/Q55615626",
        "country_qid": "Q1020"
      }
    }
  ]
}