{
  "type": "FeatureCollection",
  "features": [
    {
      "type": "Feature",
      "geometry": {
        "type": "Point",
        "coordinates": [
          -69.889888888,
          12.432333333
        ]
      },
      "properties": {
        "label": "Sunrise Solar Park",
        "type": "solar power station",
        "powerplant": "http://www.wikidata.org/entity/Q124096683",
        "country_qid": "Q21203"
      }
    }
  ]
}