{
  "type": "FeatureCollection",
  "features": [
    {
      "type": "Feature",
      "geometry": {
        "type": "Point",
        "coordinates": [
          -70.046819,
          12.563573
        ]
      },
      "properties": {
        "label": "De Oude Molen",
        "type": "Industrial building",
        "entity": "http://www.wikidata.org/entity/Q19277907",
        "country_qid": "Q21203"
      }
    },
    {
      "type": "Feature",
      "geometry": {
        "type": "Point",
        "coordinates": [
          -70.047269444,
          12.563211111
        ]
      },
      "properties": {
        "label": "De Olde Molen",
        "type": "Industrial building",
        "entity": "http://www.wikidata.org/entity/Q96573429",
        "country_qid": "Q21203"
      }
    }
  ]
}