{
  "type": "FeatureCollection",
  "features": [
    {
      "type": "Feature",
      "geometry": {
        "type": "Point",
        "coordinates": [
          6.87194,
          51.5189
        ]
      },
      "properties": {
        "label": "St.-Antony ironworks",
        "type": "Industrial building",
        "entity": "http://www.wikidata.org/entity/Q2315987",
        "country_qid": "Q27306"
      }
    },
    {
      "type": "Feature",
      "geometry": {
        "type": "Point",
        "coordinates": [
          18.9597,
          50.3014
        ]
      },
      "properties": {
        "label": "Huta Kościuszko",
        "type": "Industrial building",
        "entity": "http://www.wikidata.org/entity/Q9295161",
        "country_qid": "Q27306"
      }
    },
    {
      "type": "Feature",
      "geometry": {
        "type": "Point",
        "coordinates": [
          13.396945773,
          52.511557491
        ]
      },
      "properties": {
        "label": "Atelier Philipp Graff",
        "type": "Industrial building",
        "entity": "http://www.wikidata.org/entity/Q106636002",
        "country_qid": "Q27306"
      }
    },
    {
      "type": "Feature",
      "geometry": {
        "type": "Point",
        "coordinates": [
          13.386505411,
          52.51031402
        ]
      },
      "properties": {
        "label": "Loescher & Petsch",
        "type": "Industrial building",
        "entity": "http://www.wikidata.org/entity/Q29554378",
        "country_qid": "Q27306"
      }
    }
  ]
}