{
  "type": "FeatureCollection",
  "features": [
    {
      "type": "Feature",
      "geometry": {
        "type": "Point",
        "coordinates": [
          121.066027777,
          13.722083333
        ]
      },
      "properties": {
        "label": "Tabangao Refinery",
        "type": "Oil refinery",
        "entity": "http://www.wikidata.org/entity/Q104848936",
        "country_qid": "Q928"
      }
    }
  ]
}