{
  "type": "FeatureCollection",
  "features": [
    {
      "type": "Feature",
      "geometry": {
        "type": "Point",
        "coordinates": [
          105.79777778,
          19.34222222
        ]
      },
      "properties": {
        "label": "Nghi Son Refinery",
        "type": "Oil refinery",
        "entity": "http://www.wikidata.org/entity/Q7022321",
        "country_qid": "Q881"
      }
    },
    {
      "type": "Feature",
      "geometry": {
        "type": "Point",
        "coordinates": [
          108.82972222,
          15.3525
        ]
      },
      "properties": {
        "label": "Dung Quat refinery",
        "type": "Oil refinery",
        "entity": "http://www.wikidata.org/entity/Q3041307",
        "country_qid": "Q881"
      }
    }
  ]
}