{
  "type": "FeatureCollection",
  "features": [
    {
      "type": "Feature",
      "geometry": {
        "type": "Point",
        "coordinates": [
          23.2699,
          42.6697
        ]
      },
      "properties": {
        "label": "Electricity System Operator",
        "type": "transmission system operator (TSO)",
        "entity": "http://www.wikidata.org/entity/Q12279650",
        "country_qid": "Q219"
      }
    }
  ]
}