{
  "type": "FeatureCollection",
  "features": [
    {
      "type": "Feature",
      "geometry": {
        "type": "Point",
        "coordinates": [
          16.076216962,
          8.553685695
        ]
      },
      "properties": {
        "label": "Q134454265",
        "type": "power plant",
        "entity": "http://www.wikidata.org/entity/Q134454265",
        "country_qid": "Q657",
        "Wikidata Qid": "Q134454265"
      }
    },
    {
      "type": "Feature",
      "geometry": {
        "type": "Point",
        "coordinates": [
          15.030833333,
          12.144722222
        ]
      },
      "properties": {
        "label": "N'Djamena Amea Solar Power Station",
        "type": "power plant",
        "entity": "http://www.wikidata.org/entity/Q108782215",
        "country_qid": "Q657",
        "Wikidata Qid": "Q108782215"
      }
    },
    {
      "type": "Feature",
      "geometry": {
        "type": "Point",
        "coordinates": [
          15.036666666,
          12.386666666
        ]
      },
      "properties": {
        "label": "D'jermaya Solar Power Station",
        "type": "power plant",
        "entity": "http://www.wikidata.org/entity/Q108782310",
        "country_qid": "Q657",
        "Wikidata Qid": "Q108782310"
      }
    },
    {
      "type": "Feature",
      "geometry": {
        "type": "Point",
        "coordinates": [
          14.996111111,
          12.135305555
        ]
      },
      "properties": {
        "label": "Q56372801",
        "type": "power plant",
        "entity": "http://www.wikidata.org/entity/Q56372801",
        "country_qid": "Q657",
        "Wikidata Qid": "Q56372801"
      }
    },
    {
      "type": "Feature",
      "geometry": {
        "type": "Point",
        "coordinates": [
          16.79475,
          8.531944444
        ]
      },
      "properties": {
        "label": "Q56372802",
        "type": "power plant",
        "entity": "http://www.wikidata.org/entity/Q56372802",
        "country_qid": "Q657",
        "Wikidata Qid": "Q56372802"
      }
    },
    {
      "type": "Feature",
      "geometry": {
        "type": "Point",
        "coordinates": [
          15.1037,
          12.1017
        ]
      },
      "properties": {
        "label": "Q134429865",
        "type": "Reservoir",
        "entity": "http://www.wikidata.org/entity/Q134429865",
        "country_qid": "Q657",
        "Wikidata Qid": "Q134429865"
      }
    },
    {
      "type": "Feature",
      "geometry": {
        "type": "Point",
        "coordinates": [
          15.583055555,
          9.921111111
        ]
      },
      "properties": {
        "label": "Ancien Canal de Ham",
        "type": "Hydraulic structure",
        "entity": "http://www.wikidata.org/entity/Q31979672",
        "country_qid": "Q657",
        "Wikidata Qid": "Q31979672"
      }
    },
    {
      "type": "Feature",
      "geometry": {
        "type": "Point",
        "coordinates": [
          15.0655,
          10.8277
        ]
      },
      "properties": {
        "label": "Maga Dam",
        "type": "Hydraulic structure",
        "entity": "http://www.wikidata.org/entity/Q6729568",
        "country_qid": "Q657",
        "Wikidata Qid": "Q6729568"
      }
    },
    {
      "type": "Feature",
      "geometry": {
        "type": "Point",
        "coordinates": [
          18.5689,
          10.1723
        ]
      },
      "properties": {
        "label": "Tele-Nugar Iron Mines",
        "type": "Mine",
        "entity": "http://www.wikidata.org/entity/Q7695700",
        "country_qid": "Q657",
        "Wikidata Qid": "Q7695700"
      }
    }
  ]
}