{
  "type": "FeatureCollection",
  "features": [
    {
      "type": "Feature",
      "geometry": {
        "type": "Point",
        "coordinates": [
          5.099138888,
          52.476555555
        ]
      },
      "properties": {
        "label": "Q134170466",
        "type": "Hydraulic structure",
        "entity": "http://www.wikidata.org/entity/Q134170466",
        "country_qid": "Q29999"
      }
    },
    {
      "type": "Feature",
      "geometry": {
        "type": "Point",
        "coordinates": [
          4.7505,
          52.67475
        ]
      },
      "properties": {
        "label": "Achtersloot, Koedijk",
        "type": "Hydraulic structure",
        "entity": "http://www.wikidata.org/entity/Q131862797",
        "country_qid": "Q29999"
      }
    },
    {
      "type": "Feature",
      "geometry": {
        "type": "Point",
        "coordinates": [
          4.4535,
          51.9127
        ]
      },
      "properties": {
        "label": "Gemaal Heemraadsplein (Rotterdam)",
        "type": "Hydraulic structure",
        "entity": "http://www.wikidata.org/entity/Q130401483",
        "country_qid": "Q29999"
      }
    },
    {
      "type": "Feature",
      "geometry": {
        "type": "Point",
        "coordinates": [
          6.146938888,
          51.308608333
        ]
      },
      "properties": {
        "label": "Groeve Maalbeek (Belfeld)",
        "type": "Mine",
        "entity": "http://www.wikidata.org/entity/Q126963646",
        "country_qid": "Q29999"
      }
    }
  ]
}