{
  "type": "FeatureCollection",
  "features": [
    {
      "type": "Feature",
      "geometry": {
        "type": "Point",
        "coordinates": [
          -171.884666666,
          -13.885166666
        ]
      },
      "properties": {
        "label": "Fiaga Diesel Power Plant",
        "type": "power plant",
        "entity": "http://www.wikidata.org/entity/Q123163605",
        "country_qid": "Q683",
        "Wikidata Qid": "Q123163605"
      }
    }
  ]
}