{
  "type": "FeatureCollection",
  "features": [
    {
      "type": "Feature",
      "geometry": {
        "type": "Point",
        "coordinates": [
          -171.884666666,
          -13.885166666
        ]
      },
      "properties": {
        "label": "Fiaga Diesel Power Plant",
        "type": "power plant",
        "entity": "http://www.wikidata.org/entity/Q123163605",
        "country_qid": "Q683",
        "Wikidata Qid": "Q123163605"
      }
    },
    {
      "type": "Feature",
      "geometry": {
        "type": "Point",
        "coordinates": [
          -171.55028,
          -13.97127
        ]
      },
      "properties": {
        "label": "Afulilo Dam",
        "type": "Hydraulic structure",
        "entity": "http://www.wikidata.org/entity/Q16888271",
        "country_qid": "Q683",
        "Wikidata Qid": "Q16888271"
      }
    },
    {
      "type": "Feature",
      "geometry": {
        "type": "Point",
        "coordinates": [
          -171.766666666,
          -13.816666666
        ]
      },
      "properties": {
        "label": "Apia",
        "type": "Hydraulic structure",
        "entity": "http://www.wikidata.org/entity/Q111387110",
        "country_qid": "Q683",
        "Wikidata Qid": "Q111387110"
      }
    }
  ]
}