{
  "type": "FeatureCollection",
  "features": [
    {
      "type": "Feature",
      "geometry": {
        "type": "Point",
        "coordinates": [
          -16.63568933,
          13.29265016
        ]
      },
      "properties": {
        "label": "Brikama power station",
        "type": "power plant",
        "entity": "http://www.wikidata.org/entity/Q1601469",
        "country_qid": "Q1005",
        "Wikidata Qid": "Q1601469"
      }
    },
    {
      "type": "Feature",
      "geometry": {
        "type": "Point",
        "coordinates": [
          -15.518055555,
          13.436944444
        ]
      },
      "properties": {
        "label": "Soma Solar Power Station",
        "type": "power plant",
        "entity": "http://www.wikidata.org/entity/Q111947629",
        "country_qid": "Q1005",
        "Wikidata Qid": "Q111947629"
      }
    },
    {
      "type": "Feature",
      "geometry": {
        "type": "Point",
        "coordinates": [
          -16.696777777,
          13.454361111
        ]
      },
      "properties": {
        "label": "Kotu Power Station",
        "type": "power plant",
        "entity": "http://www.wikidata.org/entity/Q56372896",
        "country_qid": "Q1005",
        "Wikidata Qid": "Q56372896"
      }
    },
    {
      "type": "Feature",
      "geometry": {
        "type": "Point",
        "coordinates": [
          -16.690555555,
          13.306388888
        ]
      },
      "properties": {
        "label": "Jambur Solar Power Station",
        "type": "power plant",
        "entity": "http://www.wikidata.org/entity/Q125635132",
        "country_qid": "Q1005",
        "Wikidata Qid": "Q125635132"
      }
    }
  ]
}