{
  "type": "FeatureCollection",
  "features": [
    {
      "type": "Feature",
      "geometry": {
        "type": "Point",
        "coordinates": [
          9.147247,
          49.304697
        ]
      },
      "properties": {
        "label": "Q2139679",
        "type": "Factory",
        "entity": "http://www.wikidata.org/entity/Q2139679",
        "country_qid": "Q43287"
      }
    },
    {
      "type": "Feature",
      "geometry": {
        "type": "Point",
        "coordinates": [
          13.466605068,
          52.516486898
        ]
      },
      "properties": {
        "label": "Q123223147",
        "type": "Factory",
        "entity": "http://www.wikidata.org/entity/Q123223147",
        "country_qid": "Q43287"
      }
    },
    {
      "type": "Feature",
      "geometry": {
        "type": "Point",
        "coordinates": [
          9.7442467,
          52.3642717
        ]
      },
      "properties": {
        "label": "Q124694021",
        "type": "Factory",
        "entity": "http://www.wikidata.org/entity/Q124694021",
        "country_qid": "Q43287"
      }
    },
    {
      "type": "Feature",
      "geometry": {
        "type": "Point",
        "coordinates": [
          13.367995219,
          52.56872715
        ]
      },
      "properties": {
        "label": "Q118669324",
        "type": "Factory",
        "entity": "http://www.wikidata.org/entity/Q118669324",
        "country_qid": "Q43287"
      }
    },
    {
      "type": "Feature",
      "geometry": {
        "type": "Point",
        "coordinates": [
          13.364032431,
          52.582602964
        ]
      },
      "properties": {
        "label": "Gummifabrik Behrendt & Co.",
        "type": "Factory",
        "entity": "http://www.wikidata.org/entity/Q118187171",
        "country_qid": "Q43287"
      }
    },
    {
      "type": "Feature",
      "geometry": {
        "type": "Point",
        "coordinates": [
          9.692,
          52.4195
        ]
      },
      "properties": {
        "label": "Waldemar Pruss Armaturenfabrik GmbH",
        "type": "Factory",
        "entity": "http://www.wikidata.org/entity/Q124370619",
        "country_qid": "Q43287"
      }
    },
    {
      "type": "Feature",
      "geometry": {
        "type": "Point",
        "coordinates": [
          13.7086,
          51.0422
        ]
      },
      "properties": {
        "label": "Q1723859",
        "type": "Factory",
        "entity": "http://www.wikidata.org/entity/Q1723859",
        "country_qid": "Q43287"
      }
    },
    {
      "type": "Feature",
      "geometry": {
        "type": "Point",
        "coordinates": [
          7.366728649,
          51.366741108
        ]
      },
      "properties": {
        "label": "Q129652226",
        "type": "Factory",
        "entity": "http://www.wikidata.org/entity/Q129652226",
        "country_qid": "Q43287"
      }
    }
  ]
}