{
  "type": "FeatureCollection",
  "features": [
    {
      "type": "Feature",
      "geometry": {
        "type": "Point",
        "coordinates": [
          5.94803,
          49.50132
        ]
      },
      "properties": {
        "label": "Blast furnaces in Belval",
        "type": "Factory",
        "entity": "http://www.wikidata.org/entity/Q13101697",
        "country_qid": "Q32"
      }
    },
    {
      "type": "Feature",
      "geometry": {
        "type": "Point",
        "coordinates": [
          5.91275,
          49.6628
        ]
      },
      "properties": {
        "label": "Q16764835",
        "type": "Factory",
        "entity": "http://www.wikidata.org/entity/Q16764835",
        "country_qid": "Q32"
      }
    },
    {
      "type": "Feature",
      "geometry": {
        "type": "Point",
        "coordinates": [
          6.20429,
          49.59792
        ]
      },
      "properties": {
        "label": "Q105812089",
        "type": "Factory",
        "entity": "http://www.wikidata.org/entity/Q105812089",
        "country_qid": "Q32"
      }
    },
    {
      "type": "Feature",
      "geometry": {
        "type": "Point",
        "coordinates": [
          6.034931,
          49.463931
        ]
      },
      "properties": {
        "label": "Q16764618",
        "type": "Factory",
        "entity": "http://www.wikidata.org/entity/Q16764618",
        "country_qid": "Q32"
      }
    },
    {
      "type": "Feature",
      "geometry": {
        "type": "Point",
        "coordinates": [
          6.15457,
          49.86612
        ]
      },
      "properties": {
        "label": "Brasserie de Luxembourg",
        "type": "Factory",
        "entity": "http://www.wikidata.org/entity/Q28195743",
        "country_qid": "Q32"
      }
    },
    {
      "type": "Feature",
      "geometry": {
        "type": "Point",
        "coordinates": [
          5.994867,
          49.505475
        ]
      },
      "properties": {
        "label": "Q16764167",
        "type": "Factory",
        "entity": "http://www.wikidata.org/entity/Q16764167",
        "country_qid": "Q32"
      }
    },
    {
      "type": "Feature",
      "geometry": {
        "type": "Point",
        "coordinates": [
          6.1577296,
          49.6405772
        ]
      },
      "properties": {
        "label": "Q13102376",
        "type": "Factory",
        "entity": "http://www.wikidata.org/entity/Q13102376",
        "country_qid": "Q32"
      }
    },
    {
      "type": "Feature",
      "geometry": {
        "type": "Point",
        "coordinates": [
          5.8987,
          49.52756
        ]
      },
      "properties": {
        "label": "Differdange steelworks",
        "type": "Factory",
        "entity": "http://www.wikidata.org/entity/Q13102383",
        "country_qid": "Q32"
      }
    },
    {
      "type": "Feature",
      "geometry": {
        "type": "Point",
        "coordinates": [
          6.08094,
          49.46942
        ]
      },
      "properties": {
        "label": "Q13102342",
        "type": "Factory",
        "entity": "http://www.wikidata.org/entity/Q13102342",
        "country_qid": "Q32"
      }
    },
    {
      "type": "Feature",
      "geometry": {
        "type": "Point",
        "coordinates": [
          6.12581,
          49.62732
        ]
      },
      "properties": {
        "label": "Q13102417",
        "type": "Factory",
        "entity": "http://www.wikidata.org/entity/Q13102417",
        "country_qid": "Q32"
      }
    },
    {
      "type": "Feature",
      "geometry": {
        "type": "Point",
        "coordinates": [
          5.955942,
          49.500834
        ]
      },
      "properties": {
        "label": "Adolf-Emil-Hütte",
        "type": "Factory",
        "entity": "http://www.wikidata.org/entity/Q360553",
        "country_qid": "Q32"
      }
    },
    {
      "type": "Feature",
      "geometry": {
        "type": "Point",
        "coordinates": [
          6.1118183,
          49.7535021
        ]
      },
      "properties": {
        "label": "Q13105476",
        "type": "Factory",
        "entity": "http://www.wikidata.org/entity/Q13105476",
        "country_qid": "Q32"
      }
    }
  ]
}