{
  "type": "FeatureCollection",
  "features": [
    {
      "type": "Feature",
      "geometry": {
        "type": "Point",
        "coordinates": [
          105.0607431,
          9.2418219
        ]
      },
      "properties": {
        "label": "Q11962958",
        "type": "Gas-fired power station",
        "entity": "http://www.wikidata.org/entity/Q11962958",
        "country_qid": "Q881"
      }
    },
    {
      "type": "Feature",
      "geometry": {
        "type": "Point",
        "coordinates": [
          107.037,
          10.604
        ]
      },
      "properties": {
        "label": "Phú Mỹ Power Plants",
        "type": "Gas-fired power station",
        "entity": "http://www.wikidata.org/entity/Q7189879",
        "country_qid": "Q881"
      }
    },
    {
      "type": "Feature",
      "geometry": {
        "type": "Point",
        "coordinates": [
          106.8394124,
          10.643192
        ]
      },
      "properties": {
        "label": "Q11991295",
        "type": "Gas-fired power station",
        "entity": "http://www.wikidata.org/entity/Q11991295",
        "country_qid": "Q881"
      }
    },
    {
      "type": "Feature",
      "geometry": {
        "type": "Point",
        "coordinates": [
          105.063,
          9.236
        ]
      },
      "properties": {
        "label": "Ca Mau Gas-Power-Fertilizer Complex",
        "type": "Gas-fired power station",
        "entity": "http://www.wikidata.org/entity/Q5015167",
        "country_qid": "Q881"
      }
    }
  ]
}