{
  "type": "FeatureCollection",
  "features": [
    {
      "type": "Feature",
      "geometry": {
        "type": "Point",
        "coordinates": [
          -54.608888888,
          -25.42
        ]
      },
      "properties": {
        "label": "Itaipu right bank substation",
        "type": "Electrical substation",
        "entity": "http://www.wikidata.org/entity/Q53679310",
        "country_qid": "Q733"
      }
    }
  ]
}